BLADE_Deconvolution/BLADE.py
BLADE_Deconvolution/CreateSignature.py
BLADE_Deconvolution/__init__.py
StateDiscovery/__init__.py
StateDiscovery/cNMF.py
StateDiscovery/lib/__init__.py
StateDiscovery/lib/cnmf_helpers.py
StateDiscovery/lib/pymf/__init__.py
StateDiscovery/lib/pymf/base.py
StateDiscovery/lib/pymf/cnmf.py
StateDiscovery/lib/pymf/dist.py
StateDiscovery/lib/pymf/kmeans.py
Statescope/Statescope.py
Statescope/__init__.py
statescope-1.0.0.dist-info/licenses/LICENSE
statescope-1.0.0.dist-info/METADATA
statescope-1.0.0.dist-info/WHEEL
statescope-1.0.0.dist-info/top_level.txt
statescope-1.0.0.dist-info/RECORD
