Metadata-Version: 2.4
Name: Statescope
Version: 1.0.0
Summary: Statescope framework to uncover cell states from bulk RNA-seq and DNA-seq data
Author-email: Jurriaan Janssen <j.janssen4@amsterdamumc.nl>, Mischa Steketee <m.f.b.steketee@amsterdamumc.nl>, Aryamaan Bose <a.bose1@amsterdamumc.nl>, Yongsoo Kim <yo.kim@amsterdamumc.nl>
License: MIT License
Project-URL: Homepage, https://statescope.netlify.app/
Project-URL: Repository, https://github.com/tgac-vumc/Statescope
Classifier: Programming Language :: Python :: 3
Classifier: Programming Language :: Python :: 3.6
Classifier: Programming Language :: Python :: 3.7
Classifier: Programming Language :: Python :: 3.8
Classifier: License :: OSI Approved :: MIT License
Classifier: Operating System :: OS Independent
Requires-Python: >=3.10
License-File: LICENSE
Requires-Dist: numba
Requires-Dist: numpy<2.0.0
Requires-Dist: scipy
Requires-Dist: scikit-learn
Requires-Dist: joblib
Requires-Dist: pandas<2.0.0
Requires-Dist: statsmodels
Requires-Dist: autogenes>=1.0
Requires-Dist: multiprocess
Requires-Dist: anndata>0.7
Requires-Dist: torch
Requires-Dist: torchvision
Requires-Dist: seaborn
Requires-Dist: requests
Dynamic: license-file
